torrent_creator/__init__.py
torrent_creator/torrent-creator.py
torrent_creator/torrent_creator.py
torrent_creator-1.2.0.dist-info/licenses/LICENSE
torrent_creator-1.2.0.dist-info/METADATA
torrent_creator-1.2.0.dist-info/WHEEL
torrent_creator-1.2.0.dist-info/entry_points.txt
torrent_creator-1.2.0.dist-info/top_level.txt
torrent_creator-1.2.0.dist-info/RECORD
