Metadata-Version: 2.4
Name: torrent-creator
Version: 1.2.0
Summary: A Python CLI tool for creating torrent files
Home-page: https://github.com/itzrealbeluga/torrent-creator
Author: Beluga
Author-email: your.email@example.com
Classifier: Programming Language :: Python :: 3
Classifier: License :: OSI Approved :: MIT License
Classifier: Operating System :: OS Independent
Requires-Python: >=3.6
License-File: LICENSE
Requires-Dist: bencodepy
Requires-Dist: python-dotenv
Requires-Dist: tqdm
Dynamic: author
Dynamic: author-email
Dynamic: classifier
Dynamic: description
Dynamic: description-content-type
Dynamic: home-page
Dynamic: license-file
Dynamic: requires-dist
Dynamic: requires-python
Dynamic: summary
